marshmallow3_annotations/__init__.py
marshmallow3_annotations/_compat.py
marshmallow3_annotations/base.py
marshmallow3_annotations/converter.py
marshmallow3_annotations/exceptions.py
marshmallow3_annotations/registry.py
marshmallow3_annotations/scheme.py
marshmallow3_annotations/ext/__init__.py
marshmallow3_annotations/ext/attrs.py
marshmallow3_annotations/ext/namedtuple.py
marshmallow3_annotations-1.1.0.dist-info/LICENSE
marshmallow3_annotations-1.1.0.dist-info/METADATA
marshmallow3_annotations-1.1.0.dist-info/WHEEL
marshmallow3_annotations-1.1.0.dist-info/top_level.txt
marshmallow3_annotations-1.1.0.dist-info/RECORD
