Metadata-Version: 2.1
Name: marshmallow3-annotations
Version: 1.1.0
Summary: Marrying marshmallow3 and annotations
Home-page: https://github.com/dkunitsk/marshmallow3-annotations
Author: Alec Nikolas Reiter
Author-email: alecreiter@gmail.com
License: MIT
Keywords: annotations,marshmallow
Classifier: Topic :: Utilities
Classifier: Intended Audience :: Developers
Classifier: License :: OSI Approved :: MIT License
Classifier: Programming Language :: Python :: 3.6
Classifier: Programming Language :: Python :: Implementation :: CPython
License-File: LICENSE
Requires-Dist: marshmallow (>=3.0.0)
Provides-Extra: attrs
Requires-Dist: attrs ; extra == 'attrs'
